devtools_csv_json/__init__.py
devtools_csv_json-1.0.1.dist-info/METADATA
devtools_csv_json-1.0.1.dist-info/WHEEL
devtools_csv_json-1.0.1.dist-info/top_level.txt
devtools_csv_json-1.0.1.dist-info/RECORD
